Metadata-Version: 2.4
Name: ptm_pose
Version: 0.3.1
Summary: PTM-POSE: PTM Projection onto Splice Events
Home-page: https://github.com/NaegleLab/PTM-POSE/tree/main
Author: Naegle Lab
Author-email: kmn4mj@virginia.edu
License: GNU General Public License v3
Project-URL: Homepage, https://github.com/NaegleLab/PTM-POSE/
Project-URL: Issues, https://github.com/NaegleLab/PTM-POSE/issues
Project-URL: Documentation, https://naeglelab.github.io/PTM-POSE/
Keywords: PTM,splicing,bioinformatics,splicing events
Classifier: Programming Language :: Python :: 3
Classifier: Intended Audience :: Science/Research
Classifier: Operating System :: OS Independent
Requires-Python: >=3.10,<3.13
License-File: LICENSE
Requires-Dist: pandas>=2.2
Requires-Dist: numpy>=1.26
Requires-Dist: biopython>=1.78
Requires-Dist: tqdm>=4.66
Requires-Dist: scipy>=1.13
Requires-Dist: xlrd
Requires-Dist: matplotlib
Requires-Dist: seaborn
Requires-Dist: requests
Provides-Extra: full-analysis
Requires-Dist: omnipath>=1.0.0; extra == "full-analysis"
Requires-Dist: pyliftover>=0.4; extra == "full-analysis"
Requires-Dist: nease>=1.3; extra == "full-analysis"
Requires-Dist: gseapy>=1.1; extra == "full-analysis"
Requires-Dist: kinase-library>=1.3; extra == "full-analysis"
Requires-Dist: networkx>=3.3; extra == "full-analysis"
Dynamic: author
Dynamic: author-email
Dynamic: classifier
Dynamic: description
Dynamic: description-content-type
Dynamic: home-page
Dynamic: keywords
Dynamic: license
Dynamic: license-file
Dynamic: project-url
Dynamic: provides-extra
Dynamic: requires-dist
Dynamic: requires-python
Dynamic: summary
